CMakeLists.txt
MANIFEST.in
README.md
python_gnmi.cpp
setup.cfg
setup.py
CMakeModules/FindGRPC.cmake
CMakeModules/FindProtobuf.cmake
ydk/gnmi/__init__.py
ydk/gnmi/path/__init__.py
ydk/gnmi/path/gnmi_session.py
ydk/gnmi/providers/__init__.py
ydk/gnmi/providers/gnmi_provider.py
ydk/gnmi/services/__init__.py
ydk/gnmi/services/gnmi_service.py
ydk_service_gnmi.egg-info/PKG-INFO
ydk_service_gnmi.egg-info/SOURCES.txt
ydk_service_gnmi.egg-info/dependency_links.txt
ydk_service_gnmi.egg-info/not-zip-safe
ydk_service_gnmi.egg-info/requires.txt
ydk_service_gnmi.egg-info/top_level.txt