Metadata-Version: 1.1
Name: ydk-service-gnmi
Version: 0.4.0.5
Summary: YDK Python SDK for gNMI services
Home-page: https://github.com/CiscoDevNet/ydk-py
Author: Cisco Systems
Author-email: yang-dk@cisco.com
License: Apache 2.0
Keywords: yang,C++11,python bindings
Platform: UNKNOWN
Classifier: Development Status :: 3 - Alpha
Classifier: Intended Audience :: Developers
Classifier: Intended Audience :: Education
Classifier: Intended Audience :: Information Technology
Classifier: Intended Audience :: Science/Research
Classifier: Intended Audience :: System Administrators
Classifier: Topic :: Software Development :: Build Tools
Classifier: Topic :: Software Development :: Libraries
Classifier: License :: OSI Approved :: Apache Software License
Classifier: Programming Language :: Python :: 3.5
Classifier: Programming Language :: Python :: 3.6
Classifier: Programming Language :: Python :: 3.7
Classifier: Programming Language :: Python :: 3.8
Classifier: Programming Language :: C++
